izi/__init__.py
izi/api.py
izi/cli.py
izi/config.py
izi/constants.py
izi/commands/__init__.py
izi/commands/auth.py
izi/commands/clone.py
izi/commands/config.py
izi/commands/create.py
izi/commands/list.py
izi/commands/logout.py
izi/commands/push.py
izi/commands/search.py
izi/commands/whoami.py
izi/utils/__init__.py
izi/utils/frontmatter.py
izi/utils/validation.py
izi-1.0.0.dist-info/licenses/LICENSE
izi-1.0.0.dist-info/METADATA
izi-1.0.0.dist-info/WHEEL
izi-1.0.0.dist-info/entry_points.txt
izi-1.0.0.dist-info/top_level.txt
izi-1.0.0.dist-info/RECORD
