Metadata-Version: 2.4
Name: izi
Version: 1.0.0
Summary: Official CLI tool for managing prompts on gitizi.com
Author-email: Gitizi <support@gitizi.com>
License: MIT
Project-URL: Homepage, https://gitizi.com
Project-URL: Repository, https://github.com/cpaka/izi-py
Project-URL: Issues, https://github.com/cpaka/izi-py/issues
Keywords: gitizi,cli,prompts,ai,prompt-engineering,prompt-management,artificial-intelligence,llm,chatgpt,claude
Classifier: Development Status :: 4 - Beta
Classifier: Intended Audience :: Developers
Classifier: License :: OSI Approved :: MIT License
Classifier: Programming Language :: Python :: 3
Classifier: Programming Language :: Python :: 3.8
Classifier: Programming Language :: Python :: 3.9
Classifier: Programming Language :: Python :: 3.10
Classifier: Programming Language :: Python :: 3.11
Classifier: Programming Language :: Python :: 3.12
Classifier: Topic :: Software Development :: Libraries :: Python Modules
Classifier: Topic :: Utilities
Requires-Python: >=3.8
License-File: LICENSE
Requires-Dist: click>=8.0.0
Requires-Dist: requests>=2.28.0
Requires-Dist: pyyaml>=6.0
Requires-Dist: python-frontmatter>=1.0.0
Requires-Dist: rich>=13.0.0
Provides-Extra: dev
Requires-Dist: pytest>=7.0.0; extra == "dev"
Requires-Dist: pytest-cov>=4.0.0; extra == "dev"
Requires-Dist: black>=23.0.0; extra == "dev"
Requires-Dist: flake8>=6.0.0; extra == "dev"
Requires-Dist: mypy>=1.0.0; extra == "dev"
Dynamic: license-file
